{"cameraMode":{"drawMode":0,"name":"Shaded","section":"Shading Mode"},"sceneLighting":true,"audioPlay":false,"sceneViewState":{"m_AlwaysRefresh":false,"showFog":true,"showSkybox":true,"showFlares":true,"showImageEffects":true,"showParticleSystems":true,"showVisualEffectGraphs":true,"m_FxEnabled":true},"in2DMode":false,"pivot":{"x":-59.35914611816406,"y":-14.659673690795899,"z":52.646331787109378},"rotation":{"x":0.15320266783237458,"y":-0.41221100091934206,"z":0.07061632722616196,"w":0.8953568935394287},"size":46.5251350402832,"orthographic":false}